tensor_ipc/__init__.py
tensor_ipc/backends/__init__.py
tensor_ipc/backends/base_backend.py
tensor_ipc/backends/numpy_backend.py
tensor_ipc/backends/torch_backend.py
tensor_ipc/backends/torch_cuda_backend.py
tensor_ipc/core/__init__.py
tensor_ipc/core/consumer.py
tensor_ipc/core/dds.py
tensor_ipc/core/metadata.py
tensor_ipc/core/mplock.py
tensor_ipc/core/producer.py
tensor_ipc/rosext/__init__.py
tensor_ipc/rosext/pool2ros_producer.py
tensor_ipc/rosext/ros2pool_consumer.py
tensor_ipc/rosext/ros_utils.py
tensor_ipc-0.1.0.dist-info/licenses/LICENSE
tensor_ipc-0.1.0.dist-info/METADATA
tensor_ipc-0.1.0.dist-info/WHEEL
tensor_ipc-0.1.0.dist-info/top_level.txt
tensor_ipc-0.1.0.dist-info/RECORD
