Metadata-Version: 2.4
Name: tensor-ipc
Version: 0.1.0
Summary: High-performance IPC for tensor data with seamless ROS integration
Home-page: https://github.com/danielhou315/tensor-ipc
Author: Daniel Hou
Author-email: Daniel Hou <houhd@umich.edu>
License: MIT License
Project-URL: Homepage, https://github.com/danielhou315/tensor-ipc
Project-URL: Repository, https://github.com/danielhou315/tensor-ipc.git
Project-URL: Issues, https://github.com/danielhou315/tensor-ipc/issues
Classifier: Development Status :: 3 - Alpha
Classifier: Intended Audience :: Developers
Classifier: License :: OSI Approved :: MIT License
Classifier: Operating System :: POSIX :: Linux
Classifier: Programming Language :: Python :: 3
Classifier: Programming Language :: Python :: 3.8
Classifier: Programming Language :: Python :: 3.9
Classifier: Programming Language :: Python :: 3.10
Classifier: Topic :: Scientific/Engineering :: Artificial Intelligence
Classifier: Topic :: Software Development :: Libraries :: Python Modules
Classifier: Topic :: System :: Networking
Requires-Python: >=3.8
License-File: LICENSE
Requires-Dist: numpy>=1.21.0
Requires-Dist: cyclonedds==0.10.5
Requires-Dist: posix-ipc>=1.0.0
Provides-Extra: torch
Requires-Dist: torch>=1.10.0; extra == "torch"
Provides-Extra: dev
Requires-Dist: pytest>=7.0; extra == "dev"
Provides-Extra: test
Requires-Dist: pytest>=7.0; extra == "test"
Provides-Extra: all
Requires-Dist: torch>=1.10.0; extra == "all"
Dynamic: author
Dynamic: home-page
Dynamic: license-file
Dynamic: requires-python
